arithop/__init__.py
arithop/__main__.py
arithop/operations.py
arithoperation/__init__.py
arithoperation/__main__.py
arithoperation/operations.py
test/test_operations.py
arithoperator-1.0.1.dist-info/METADATA
arithoperator-1.0.1.dist-info/WHEEL
arithoperator-1.0.1.dist-info/entry_points.txt
arithoperator-1.0.1.dist-info/top_level.txt
arithoperator-1.0.1.dist-info/RECORD
